MANIFEST.in
setup.cfg
setup.py
versioneer.py
JMS_Utils.egg-info/PKG-INFO
JMS_Utils.egg-info/SOURCES.txt
JMS_Utils.egg-info/dependency_links.txt
JMS_Utils.egg-info/requires.txt
JMS_Utils.egg-info/top_level.txt
jms_utils/__init__.py
jms_utils/_version.py
jms_utils/app.py
jms_utils/compat.py
jms_utils/config.py
jms_utils/crypto.py
jms_utils/exceptions.py
jms_utils/helpers.py
jms_utils/logger.py
jms_utils/paths.py
jms_utils/system.py
jms_utils/terminal.py