Metadata-Version: 1.1
Name: JMS-Utils
Version: 1.0.2
Summary: Various utility functions
Home-page: https://github.com/JohnyMoSwag/jms-utils
Author: Johny Mo Swag
Author-email: johnymoswag@gmail.com
License: MIT
Download-URL: https://github.com/JohnyMoSwag/jms-utils/archive/master.zip
Platform: UNKNOWN
Classifier: Development Status :: 4 - Beta
Classifier: Operating System :: OS Independent
Classifier: Environment :: Console
Classifier: Intended Audience :: Developers
Classifier: License :: OSI Approved :: MIT License
Classifier: Programming Language :: Python :: 2.7
